odoo/addons/pos_tare/README.rst
odoo/addons/pos_tare/__init__.py
odoo/addons/pos_tare/__manifest__.py
odoo/addons/pos_tare/data/barcode_rule.xml
odoo/addons/pos_tare/demo/product_product.xml
odoo/addons/pos_tare/i18n/es.po
odoo/addons/pos_tare/i18n/fr.po
odoo/addons/pos_tare/i18n/it.po
odoo/addons/pos_tare/i18n/pos_tare.pot
odoo/addons/pos_tare/models/__init__.py
odoo/addons/pos_tare/models/barcode_rule.py
odoo/addons/pos_tare/models/pos_config.py
odoo/addons/pos_tare/models/pos_order_line.py
odoo/addons/pos_tare/models/product_template.py
odoo/addons/pos_tare/readme/CONTRIBUTORS.rst
odoo/addons/pos_tare/readme/DESCRIPTION.rst
odoo/addons/pos_tare/readme/USAGE.rst
odoo/addons/pos_tare/static/description/icon.png
odoo/addons/pos_tare/static/description/index.html
odoo/addons/pos_tare/static/description/order.png
odoo/addons/pos_tare/static/description/pos_tare.png
odoo/addons/pos_tare/static/description/pos_ticket.png
odoo/addons/pos_tare/static/description/product_template.png
odoo/addons/pos_tare/static/src/css/pos_tare.css
odoo/addons/pos_tare/static/src/js/db.js
odoo/addons/pos_tare/static/src/js/models.js
odoo/addons/pos_tare/static/src/js/screens.js
odoo/addons/pos_tare/static/src/js/tools.js
odoo/addons/pos_tare/static/src/xml/pos_tare.xml
odoo/addons/pos_tare/views/templates.xml
odoo/addons/pos_tare/views/view_pos_config.xml
odoo/addons/pos_tare/views/view_pos_order.xml
odoo/addons/pos_tare/views/view_product_template.xml
odoo12_addon_pos_tare-12.0.1.0.4.dist-info/METADATA
odoo12_addon_pos_tare-12.0.1.0.4.dist-info/WHEEL
odoo12_addon_pos_tare-12.0.1.0.4.dist-info/top_level.txt
odoo12_addon_pos_tare-12.0.1.0.4.dist-info/RECORD
